{
  "exam": "si",
  "generatedDate": "2026-07-16",
  "generatedAt": "2026-07-16T14:31:01.204Z",
  "model": "llama-3.1-8b-instant",
  "provider": "groq",
  "source": "ai_generated",
  "reviewStatus": "pending",
  "totalQuestions": 50,
  "subjects": {
    "gs": {
      "gs-polity": {
        "topicName": "Indian Constitution & Polity",
        "subjectName": "General Studies",
        "questions": [
          {
            "question": "Which part of the Indian Constitution deals with the Fundamental Rights?",
            "options": [
              "Part III",
              "Part IV",
              "Part V",
              "Part VI"
            ],
            "correctIndex": 0,
            "explanation": "Part III of the Constitution deals with the Fundamental Rights.",
            "difficulty": "Medium",
            "topicId": "gs-polity",
            "source": "ai_generated",
            "generatedDate": "2026-07-16"
          },
          {
            "question": "Which of the following is a feature of the West Bengal Panchayat Act, 1973?",
            "options": [
              "Gram Panchayat has 7 members",
              "Gram Panchayat has 2 members",
              "Gram Panchayat has 3 members",
              "Gram Panchayat has 5 members"
            ],
            "correctIndex": 2,
            "explanation": "Gram Panchayat has 3 members as per the West Bengal Panchayat Act, 1973.",
            "difficulty": "Medium",
            "topicId": "gs-polity",
            "source": "ai_generated",
            "generatedDate": "2026-07-16"
          },
          {
            "question": "The provisions related to the election of the West Bengal Governor are mentioned in the:",
            "options": [
              "Article 163",
              "Article 164",
              "Article 165",
              "Article 166"
            ],
            "correctIndex": 3,
            "explanation": "Article 166 of the Indian Constitution mentions the provisions related to the election of the Governor.",
            "difficulty": "Medium",
            "topicId": "gs-polity",
            "source": "ai_generated",
            "generatedDate": "2026-07-16"
          },
          {
            "question": "Which of the following is a fundamental duty as per the Indian Constitution?",
            "options": [
              "To abide by the Constitution and respect its ideals and institutions",
              "To cherish and follow the noble ideals which inspired our national struggle for freedom",
              "To safeguard public property and to abjure violence",
              "All of the above"
            ],
            "correctIndex": 3,
            "explanation": "All of the above are fundamental duties as per the Indian Constitution.",
            "difficulty": "Medium",
            "topicId": "gs-polity",
            "source": "ai_generated",
            "generatedDate": "2026-07-16"
          },
          {
            "question": "The term of the West Bengal Legislative Assembly is:",
            "options": [
              "6 years",
              "5 years",
              "4 years",
              "3 years"
            ],
            "correctIndex": 3,
            "explanation": "The term of the West Bengal Legislative Assembly is 5 years.",
            "difficulty": "Medium",
            "topicId": "gs-polity",
            "source": "ai_generated",
            "generatedDate": "2026-07-16"
          }
        ],
        "questionCount": 5
      },
      "gs-freedom": {
        "topicName": "Indian Freedom Struggle & Bengal",
        "subjectName": "General Studies",
        "questions": [
          {
            "question": "Which of the following leaders played a key role in the Swadeshi Movement in Bengal?",
            "options": [
              "Aurobindo Ghosh",
              "Subhas Chandra Bose",
              "Pandit Madan Mohan Malaviya",
              "Lokmanya Tilak"
            ],
            "correctIndex": 2,
            "explanation": "Pandit Madan Mohan Malaviya was a prominent leader in the movement.",
            "difficulty": "Medium",
            "topicId": "gs-freedom",
            "source": "ai_generated",
            "generatedDate": "2026-07-16"
          },
          {
            "question": "What was the name of the first Indian magazine published in Bengal that advocated for Indian independence?",
            "options": [
              "Bengal Lights",
              "Banglar Bani",
              "The Bengalee",
              "Bandemataram"
            ],
            "correctIndex": 3,
            "explanation": "Bandemataram was the first magazine to advocate for Indian independence.",
            "difficulty": "Medium",
            "topicId": "gs-freedom",
            "source": "ai_generated",
            "generatedDate": "2026-07-16"
          },
          {
            "question": "Who led the Non-Cooperation Movement in Bengal?",
            "options": [
              "C.R. Das",
              "Satish Chandra Mukherjee",
              "Bipin Chandra Pal",
              "Vishnu Shastri Pandit"
            ],
            "correctIndex": 0,
            "explanation": "C.R. Das led the Non-Cooperation Movement in Bengal.",
            "difficulty": "Medium",
            "topicId": "gs-freedom",
            "source": "ai_generated",
            "generatedDate": "2026-07-16"
          },
          {
            "question": "Which of the following events took place in Bengal and marked a significant milestone in the Indian freedom struggle?",
            "options": [
              "The Champaran Satyagraha",
              "The Non-Cooperation Movement",
              "The Quit India Movement",
              "The Bengal Partition"
            ],
            "correctIndex": 3,
            "explanation": "The Bengal Partition was a significant event in the Indian freedom struggle that took place in Bengal.",
            "difficulty": "Medium",
            "topicId": "gs-freedom",
            "source": "ai_generated",
            "generatedDate": "2026-07-16"
          },
          {
            "question": "Who was the president of the Indian National Congress during the Bengal Provincial Conference?",
            "options": [
              "Womesh Chandra Bonnerjee",
              "Dinanath Bhattacharya",
              "Surendranath Banerjee",
              "Abdul Rasul"
            ],
            "correctIndex": 2,
            "explanation": "Surendranath Banerjee was the president of the Indian National Congress during the Bengal Provincial Conference.",
            "difficulty": "Medium",
            "topicId": "gs-freedom",
            "source": "ai_generated",
            "generatedDate": "2026-07-16"
          }
        ],
        "questionCount": 5
      },
      "gs-wb-geo": {
        "topicName": "West Bengal Geography",
        "subjectName": "General Studies",
        "questions": [
          {
            "question": "Which river forms the border between West Bengal and Bangladesh?",
            "options": [
              "Ganges River",
              "Mahananda River",
              "Torsa River",
              "Padma River"
            ],
            "correctIndex": 0,
            "explanation": "The Ganges River serves as the international border between India and Bangladesh in the western part of West Bengal.",
            "difficulty": "Medium",
            "topicId": "gs-wb-geo",
            "source": "ai_generated",
            "generatedDate": "2026-07-16"
          },
          {
            "question": "Which mountain range runs along the northern border of West Bengal?",
            "options": [
              "Himalayas",
              "Aravalli Range",
              "Eastern Ghats",
              "Patkai Range"
            ],
            "correctIndex": 0,
            "explanation": "The Himalayan mountain range forms the northern boundary of West Bengal.",
            "difficulty": "Medium",
            "topicId": "gs-wb-geo",
            "source": "ai_generated",
            "generatedDate": "2026-07-16"
          },
          {
            "question": "What is the largest island in the Sundarbans region of West Bengal?",
            "options": [
              "Hollong Island",
              "Sagardwip Island",
              "Gangasagar Island",
              "Narikeljunga Island"
            ],
            "correctIndex": 2,
            "explanation": "The Gangasagar Island is the largest island in the Sundarbans region of West Bengal.",
            "difficulty": "Medium",
            "topicId": "gs-wb-geo",
            "source": "ai_generated",
            "generatedDate": "2026-07-16"
          },
          {
            "question": "Which of the following rivers flows through the Darjeeling Himalayan hill region of West Bengal?",
            "options": [
              "Tista River",
              "Brahmaputra River",
              "Mahananda River",
              "Subarnarekha River"
            ],
            "correctIndex": 0,
            "explanation": "The Tista River flows through the Darjeeling Himalayan hill region of West Bengal.",
            "difficulty": "Medium",
            "topicId": "gs-wb-geo",
            "source": "ai_generated",
            "generatedDate": "2026-07-16"
          },
          {
            "question": "What is the name of the wetland located near Kolkata in West Bengal?",
            "options": [
              "Sundarbans Wetland",
              "Kolkata Wetland",
              "Bhagirathi-Hooghly Estuarine Wetland",
              "Dakshin Dinajpur Wetland"
            ],
            "correctIndex": 2,
            "explanation": "The Bhagirathi-Hooghly Estuarine Wetland is located near Kolkata in West Bengal.",
            "difficulty": "Medium",
            "topicId": "gs-wb-geo",
            "source": "ai_generated",
            "generatedDate": "2026-07-16"
          }
        ],
        "questionCount": 5
      },
      "gs-current": {
        "topicName": "Current Affairs (Last 12 Months)",
        "subjectName": "General Studies",
        "questions": [
          {
            "question": "Which of the following festivals was declared as a state festival in West Bengal in 2025?",
            "options": [
              "Durga Puja",
              "Diwali",
              "Lakshmi Puja",
              "Swami Vivekananda's Birthday"
            ],
            "correctIndex": 1,
            "explanation": "Diwali was declared as a state festival in West Bengal in 2025.",
            "difficulty": "Medium",
            "topicId": "gs-current",
            "source": "ai_generated",
            "generatedDate": "2026-07-16"
          },
          {
            "question": "What is the name of the newly launched mobile app by the Government of West Bengal for citizen services?",
            "options": [
              "Sakshatrata",
              "Swasthya",
              "Disha",
              "Utkarsh"
            ],
            "correctIndex": 0,
            "explanation": "The Government of West Bengal launched a mobile app named Sakshatrata for citizen services.",
            "difficulty": "Easy",
            "topicId": "gs-current",
            "source": "ai_generated",
            "generatedDate": "2026-07-16"
          },
          {
            "question": "Who was appointed as the new Chief Minister of West Bengal in 2025?",
            "options": [
              "Mamata Banerjee",
              "Suvendu Adhikari",
              "Abhishek Banerjee",
              "Shubhendu Adhikari"
            ],
            "correctIndex": 0,
            "explanation": "Mamata Banerjee was reappointed as the Chief Minister of West Bengal in 2025.",
            "difficulty": "Medium",
            "topicId": "gs-current",
            "source": "ai_generated",
            "generatedDate": "2026-07-16"
          },
          {
            "question": "Which of the following rivers is the main source of drinking water for the city of Kolkata?",
            "options": [
              "Ganges",
              "Brahmaputra",
              "Hooghly",
              "Damodar"
            ],
            "correctIndex": 2,
            "explanation": "The Hooghly River is the main source of drinking water for the city of Kolkata.",
            "difficulty": "Easy",
            "topicId": "gs-current",
            "source": "ai_generated",
            "generatedDate": "2026-07-16"
          },
          {
            "question": "What is the name of the major project launched by the West Bengal government to improve the healthcare infrastructure in the state?",
            "options": [
              "Ayushman Bharat",
              "Swasthya Yojana",
              "Niramaya",
              "Disha"
            ],
            "correctIndex": 1,
            "explanation": "The Swasthya Yojana is a major project launched by the West Bengal government to improve the healthcare infrastructure in the state.",
            "difficulty": "Medium",
            "topicId": "gs-current",
            "source": "ai_generated",
            "generatedDate": "2026-07-16"
          }
        ],
        "questionCount": 5
      },
      "gs-wb-schemes": {
        "topicName": "West Bengal Government Schemes",
        "subjectName": "General Studies",
        "questions": [
          {
            "question": "What is the main objective of the 'Sabooj Sathi' scheme launched by the West Bengal government?",
            "options": [
              "To provide free cycles to school-going girls",
              "To provide free bicycles to school-going boys",
              "To provide free laptops to school-going students",
              "To provide free books to school-going students"
            ],
            "correctIndex": 0,
            "explanation": "To provide free cycles to school-going girls.",
            "difficulty": "Medium",
            "topicId": "gs-wb-schemes",
            "source": "ai_generated",
            "generatedDate": "2026-07-16"
          },
          {
            "question": "Which of the following West Bengal government schemes aims to provide housing to the urban poor?",
            "options": [
              "Jamin Rin Pariyojna",
              "Sarva Shiksha Mission",
              "Uchched Pradhan Mantri Awas Yojana",
              "Swasthya Bhavan"
            ],
            "correctIndex": 2,
            "explanation": "Uchched Pradhan Mantri Awas Yojana.",
            "difficulty": "Medium",
            "topicId": "gs-wb-schemes",
            "source": "ai_generated",
            "generatedDate": "2026-07-16"
          },
          {
            "question": "The West Bengal government's 'Kanyashree Prakalpa' scheme is aimed at",
            "options": [
              "Empowering women through education",
              "Providing financial assistance to pregnant women",
              "Giving scholarships to meritorious students",
              "Encouraging girl child education"
            ],
            "correctIndex": 0,
            "explanation": "Empowering women through education.",
            "difficulty": "Medium",
            "topicId": "gs-wb-schemes",
            "source": "ai_generated",
            "generatedDate": "2026-07-16"
          },
          {
            "question": "Which of the following is a key feature of the West Bengal government's 'Krishi Raksha Yojana' scheme?",
            "options": [
              "Crop insurance for farmers",
              "Interest subvention for farmers",
              "Subsidized irrigation facilities",
              "Drought relief for farmers"
            ],
            "correctIndex": 0,
            "explanation": "Crop insurance for farmers.",
            "difficulty": "Medium",
            "topicId": "gs-wb-schemes",
            "source": "ai_generated",
            "generatedDate": "2026-07-16"
          },
          {
            "question": "The 'Swasthya Bhavan' is a key initiative of the West Bengal government, primarily aimed at",
            "options": [
              "Improving healthcare infrastructure in rural areas",
              "Providing free healthcare services to the poor",
              "Promoting health awareness through campaigns",
              "Facilitating medical tourism in West Bengal"
            ],
            "correctIndex": 1,
            "explanation": "Providing free healthcare services to the poor.",
            "difficulty": "Medium",
            "topicId": "gs-wb-schemes",
            "source": "ai_generated",
            "generatedDate": "2026-07-16"
          }
        ],
        "questionCount": 5
      }
    },
    "math": {
      "math-interest": {
        "topicName": "Simple & Compound Interest",
        "subjectName": "Arithmetic",
        "questions": [
          {
            "question": "A money lender gives ₹ 12,000 at 12% per annum compound interest. The amount to be returned after 2 years is?",
            "options": [
              "₹ 14,160.00",
              "₹ 14,163.84",
              "₹ 14,163.36",
              "₹ 14,165.00"
            ],
            "correctIndex": 1,
            "explanation": "Applying the compound interest formula.",
            "difficulty": "Medium",
            "topicId": "math-interest",
            "source": "ai_generated",
            "generatedDate": "2026-07-16"
          },
          {
            "question": "What is the simple interest on ₹ 7,500 for 1 year at 8% per annum?",
            "options": [
              "₹ 600.00",
              "₹ 600.50",
              "₹ 600.00",
              "₹ 600.60"
            ],
            "correctIndex": 0,
            "explanation": "Using the simple interest formula.",
            "difficulty": "Easy",
            "topicId": "math-interest",
            "source": "ai_generated",
            "generatedDate": "2026-07-16"
          },
          {
            "question": "If the simple interest on a certain sum of money at 10% per annum for 3 years is ₹ 1,500. What is the sum?",
            "options": [
              "₹ 15,000.00",
              "₹ 15,000.25",
              "₹ 15,000.00",
              "₹ 15,000.50"
            ],
            "correctIndex": 0,
            "explanation": "Using the simple interest formula to find the principal.",
            "difficulty": "Medium",
            "topicId": "math-interest",
            "source": "ai_generated",
            "generatedDate": "2026-07-16"
          },
          {
            "question": "A sum of ₹ 5,000 is invested at 5% per annum compound interest. What is the amount after 3 years?",
            "options": [
              "₹ 5,531.25",
              "₹ 5,531.30",
              "₹ 5,531.25",
              "₹ 5,531.35"
            ],
            "correctIndex": 0,
            "explanation": "Applying the compound interest formula.",
            "difficulty": "Medium",
            "topicId": "math-interest",
            "source": "ai_generated",
            "generatedDate": "2026-07-16"
          },
          {
            "question": "A person has to pay an amount of ₹ 10,000 after 3 years at 5% per annum compound interest. What is the amount to be paid now?",
            "options": [
              "₹ 9,668.42",
              "₹ 9,668.30",
              "₹ 9,668.42",
              "₹ 9,668.50"
            ],
            "correctIndex": 0,
            "explanation": "Using the compound interest formula to find the present amount.",
            "difficulty": "Medium",
            "topicId": "math-interest",
            "source": "ai_generated",
            "generatedDate": "2026-07-16"
          }
        ],
        "questionCount": 5
      },
      "math-tw": {
        "topicName": "Time, Work & Pipes",
        "subjectName": "Arithmetic",
        "questions": [
          {
            "question": "A person can complete 1/5th of the work in 2 hours. How much time will he take to complete 3/4th of the work?",
            "options": [
              "8 hours",
              "6 hours",
              "4 hours",
              "10 hours"
            ],
            "correctIndex": 2,
            "explanation": "Work done is directly proportional to time taken.",
            "difficulty": "Medium",
            "topicId": "math-tw",
            "source": "ai_generated",
            "generatedDate": "2026-07-16"
          },
          {
            "question": "A pipe can fill 1/4th of a tank in 2 hours. If 3 such pipes are connected, how long will it take to fill the tank?",
            "options": [
              "4 hours",
              "3 hours",
              "6 hours",
              "8 hours"
            ],
            "correctIndex": 1,
            "explanation": "Work done is inversely proportional to time taken.",
            "difficulty": "Medium",
            "topicId": "math-tw",
            "source": "ai_generated",
            "generatedDate": "2026-07-16"
          },
          {
            "question": "A man can do a work in 10 days. If he works for 4 hours a day, how many days will he take to complete the work?",
            "options": [
              "20 days",
              "12 days",
              "15 days",
              "25 days"
            ],
            "correctIndex": 2,
            "explanation": "Time taken is directly proportional to work done.",
            "difficulty": "Medium",
            "topicId": "math-tw",
            "source": "ai_generated",
            "generatedDate": "2026-07-16"
          },
          {
            "question": "A pump can fill 2/3rd of a tank in 4 hours. How much time will it take to fill 2/3rd of another tank?",
            "options": [
              "2 hours",
              "4 hours",
              "6 hours",
              "8 hours"
            ],
            "correctIndex": 0,
            "explanation": "Time taken is directly proportional to work done.",
            "difficulty": "Medium",
            "topicId": "math-tw",
            "source": "ai_generated",
            "generatedDate": "2026-07-16"
          },
          {
            "question": "A person can finish 1/4th of the work in 3 hours. If he works at the same rate, how much time will he take to finish 3/4th of the work?",
            "options": [
              "9 hours",
              "12 hours",
              "15 hours",
              "18 hours"
            ],
            "correctIndex": 2,
            "explanation": "Work done is directly proportional to time taken.",
            "difficulty": "Medium",
            "topicId": "math-tw",
            "source": "ai_generated",
            "generatedDate": "2026-07-16"
          }
        ],
        "questionCount": 5
      },
      "math-tsd": {
        "topicName": "Time, Speed & Distance",
        "subjectName": "Arithmetic",
        "questions": [
          {
            "question": "A train travels from Howrah to Bardhaman at an average speed of 60 km/h. If the distance between the two cities is 107 km, how long does the journey take?",
            "options": [
              "3 hours",
              "3.5 hours",
              "4 hours",
              "4.5 hours"
            ],
            "correctIndex": 1,
            "explanation": "Time taken is calculated by dividing distance by speed.",
            "difficulty": "Medium",
            "topicId": "math-tsd",
            "source": "ai_generated",
            "generatedDate": "2026-07-16"
          },
          {
            "question": "If a bus covers a distance of 240 km in 8 hours, what is its average speed?",
            "options": [
              "25 km/h",
              "30 km/h",
              "35 km/h",
              "40 km/h"
            ],
            "correctIndex": 2,
            "explanation": "Average speed is calculated by dividing distance by time.",
            "difficulty": "Easy",
            "topicId": "math-tsd",
            "source": "ai_generated",
            "generatedDate": "2026-07-16"
          },
          {
            "question": "A car travels from Kolkata to Digha at an average speed of 80 km/h. If the distance between the two cities is 220 km, how long does the journey take?",
            "options": [
              "2.5 hours",
              "2.75 hours",
              "3 hours",
              "3.25 hours"
            ],
            "correctIndex": 0,
            "explanation": "Time taken is calculated by dividing distance by speed.",
            "difficulty": "Medium",
            "topicId": "math-tsd",
            "source": "ai_generated",
            "generatedDate": "2026-07-16"
          },
          {
            "question": "A speed limit signs states that the maximum speed limit on the Kolkata-Airport road is 50 km/h. If a driver covers a distance of 15 km in 30 minutes, has he exceeded the speed limit?",
            "options": [
              "Yes",
              "No"
            ],
            "correctIndex": "No",
            "explanation": "Speed is calculated by dividing distance by time and rounding to the nearest integer.",
            "difficulty": "Easy",
            "topicId": "math-tsd",
            "source": "ai_generated",
            "generatedDate": "2026-07-16"
          },
          {
            "question": "A motorcyclist travels from Siliguri to Darjeeling at an average speed of 40 km/h. If the distance between the two cities is 70 km, how long does the journey take?",
            "options": [
              "1.75 hours",
              "2 hours",
              "2.25 hours",
              "2.5 hours"
            ],
            "correctIndex": 2,
            "explanation": "Time taken is calculated by dividing distance by speed.",
            "difficulty": "Medium",
            "topicId": "math-tsd",
            "source": "ai_generated",
            "generatedDate": "2026-07-16"
          }
        ],
        "questionCount": 5
      }
    },
    "reasoning": {
      "rs-direction": {
        "topicName": "Direction Sense",
        "subjectName": "Reasoning",
        "questions": [
          {
            "question": "A man walks 6 km north, then 3 km east, then 4 km south. In which direction is he from the starting point?",
            "options": [
              "North",
              "East",
              "South-West",
              "North-East"
            ],
            "correctIndex": 2,
            "explanation": "The net displacement is 2 km south and 3 km east.",
            "difficulty": "Medium",
            "topicId": "rs-direction",
            "source": "ai_generated",
            "generatedDate": "2026-07-16"
          },
          {
            "question": "If it takes 5 hours to reach Belghoria Expressway from Sealdah by bus, and the return journey takes 3 hours, how much time will it take to reach Sealdah from Belghoria Expressway if the speed of the bus is doubled?",
            "options": [
              "6 hours",
              "3 hours",
              "4.5 hours",
              "2.5 hours"
            ],
            "correctIndex": 0,
            "explanation": "Time is inversely proportional to speed.",
            "difficulty": "Medium",
            "topicId": "rs-direction",
            "source": "ai_generated",
            "generatedDate": "2026-07-16"
          },
          {
            "question": "A person walks 120 m due east, then 90 m due north, and finally 80 m due west. How far is he from the starting point?",
            "options": [
              "110 m",
              "90 m",
              "120 m",
              "80 m"
            ],
            "correctIndex": 0,
            "explanation": "The net displacement is 10 m north.",
            "difficulty": "Medium",
            "topicId": "rs-direction",
            "source": "ai_generated",
            "generatedDate": "2026-07-16"
          },
          {
            "question": "If a man walks 4 km in 2 hours and then covers a certain distance in 2 hours, but in the opposite direction, then his average speed for the entire journey is 1.5 km/h. What is the speed of the man when he walks in the opposite direction?",
            "options": [
              "1 km/h",
              "2 km/h",
              "3 km/h",
              "4 km/h"
            ],
            "correctIndex": 1,
            "explanation": "Average speed is the total distance divided by the total time.",
            "difficulty": "Medium",
            "topicId": "rs-direction",
            "source": "ai_generated",
            "generatedDate": "2026-07-16"
          },
          {
            "question": "A car travels from Howrah to Bally, a distance of 15 km, in 30 minutes. How much time will it take to cover a distance of 45 km?",
            "options": [
              "1 hour",
              "45 minutes",
              "1.5 hours",
              "2 hours"
            ],
            "correctIndex": 0,
            "explanation": "Distance is directly proportional to time.",
            "difficulty": "Medium",
            "topicId": "rs-direction",
            "source": "ai_generated",
            "generatedDate": "2026-07-16"
          }
        ],
        "questionCount": 5
      },
      "rs-series": {
        "topicName": "Number & Letter Series",
        "subjectName": "Reasoning",
        "questions": [
          {
            "question": "In the series 2, 6, 12, 20, 30, which will be the next number?",
            "options": [
              "8",
              "10",
              "12",
              "14"
            ],
            "correctIndex": 1,
            "explanation": "The pattern is an increase by 4, 6, 8, 10, and so on.",
            "difficulty": "Medium",
            "topicId": "rs-series",
            "source": "ai_generated",
            "generatedDate": "2026-07-16"
          },
          {
            "question": "Which number will replace the question mark in the series 1, 2, 4, 7, 11, 16, ?",
            "options": [
              "22",
              "20",
              "21",
              "23"
            ],
            "correctIndex": 2,
            "explanation": "The pattern involves adding consecutive integers, starting from 1.",
            "difficulty": "Medium",
            "topicId": "rs-series",
            "source": "ai_generated",
            "generatedDate": "2026-07-16"
          },
          {
            "question": "In the series A, B, C, D, E, F, G, H, I, J, what comes next after H?",
            "options": [
              "K",
              "I",
              "J",
              "L"
            ],
            "correctIndex": 3,
            "explanation": "The pattern involves the English alphabet.",
            "difficulty": "Medium",
            "topicId": "rs-series",
            "source": "ai_generated",
            "generatedDate": "2026-07-16"
          },
          {
            "question": "The numbers given in a series are: 3, 6, 12, 24, 48, ?",
            "options": [
              "24",
              "48",
              "96",
              "192"
            ],
            "correctIndex": 2,
            "explanation": "The pattern involves doubling the previous number.",
            "difficulty": "Medium",
            "topicId": "rs-series",
            "source": "ai_generated",
            "generatedDate": "2026-07-16"
          },
          {
            "question": "In the following series, what comes next after 7? 1, 2, 4, 7, 11, 16, ?",
            "options": [
              "22",
              "21",
              "22",
              "23"
            ],
            "correctIndex": 1,
            "explanation": "The pattern involves adding consecutive integers, starting from 1.",
            "difficulty": "Medium",
            "topicId": "rs-series",
            "source": "ai_generated",
            "generatedDate": "2026-07-16"
          }
        ],
        "questionCount": 5
      }
    }
  }
}